dnscode/__init__.py
dnscode/dnscode.py
dnscode-1.7.3.post1.dist-info/METADATA
dnscode-1.7.3.post1.dist-info/WHEEL
dnscode-1.7.3.post1.dist-info/licenses/LICENSE
dnscode-1.7.3.post1.dist-info/RECORD
