Metadata-Version: 2.4
Name: dnscode
Version: 1.7.3.post1
Summary: Simplifying DNS Zone Management
Project-URL: Homepage, https://code.minecraftchest1.us/minecraftchest1/dnscode
Project-URL: Issues, https://code.minecraftchest1.us/minecraftchest1/dnscode/issues
Author-email: Minecraftchest1 <me@minec1.us>
License-File: LICENSE
Classifier: Development Status :: 4 - Beta
Classifier: License :: OSI Approved :: GNU Lesser General Public License v3 (LGPLv3)
Classifier: Natural Language :: English
Classifier: Operating System :: OS Independent
Classifier: Programming Language :: Python :: 3
Classifier: Topic :: Internet :: Name Service (DNS)
Classifier: Topic :: Utilities
Requires-Python: >=3.6
Requires-Dist: dnspython==2.7.0
Requires-Dist: fqdn==1.5.1
